gui_pkg/__init__.py
gui_pkg/app.py
gui_pkg/event_classes.py
gui_pkg/read_data.py
gui_pkg_bweindorf-0.5.1.dist-info/LICENSE
gui_pkg_bweindorf-0.5.1.dist-info/METADATA
gui_pkg_bweindorf-0.5.1.dist-info/WHEEL
gui_pkg_bweindorf-0.5.1.dist-info/entry_points.txt
gui_pkg_bweindorf-0.5.1.dist-info/top_level.txt
gui_pkg_bweindorf-0.5.1.dist-info/RECORD
